Computer_Organization_&_Architecture/Ch-8 june21/exer/8_2_3.v
module fsm2_behavioral (
    output reg Dout,
    input wire clk,
    input wire Reset,
    input wire Din
);
    parameter S0 = 2'b00;
    parameter S1 = 2'b01;
    parameter S2 = 2'b10;
    parameter S3 = 2'b11;

    reg [1:0] state, next_state;

    always @(posedge clk or posedge Reset) begin
        if (Reset) begin
            state <= S0;
            Dout <= 1'b0;
        end else begin
            state <= next_state;
        end
    end

    always @(*) begin
        case (state)
            S0: begin
                if (Din) begin
                    next_state = S1;
                    Dout = 1'b1;
                end else begin
                    next_state = S0;
                    Dout = 1'b0;
                end
            end
            S1: begin
                if (Din) begin
                    next_state = S3;
                    Dout = 1'b0;
                end else begin
                    next_state = S2;
                    Dout = 1'b1;
                end
            end
            S2: begin
                if (Din) begin
                    next_state = S3;
                    Dout = 1'b1;
                end else begin
                    next_state = S0;
                    Dout = 1'b0;
                end
            end
            S3: begin
                if (Din) begin
                    next_state = S0;
                    Dout = 1'b1;
                end else begin
                    next_state = S3;
                    Dout = 1'b0;
                end
            end
            default: next_state = S0;
        endcase
    end

endmodule

module fsm2_behavioral_tb;

    parameter CLK_PERIOD = 10;

    reg clk;
    reg Reset;
    reg Din;
    wire Dout;

    fsm2_behavioral DUT (
        .clk(clk),
        .Reset(Reset),
        .Din(Din),
        .Dout(Dout)
    );

    always #((CLK_PERIOD / 2)) clk <= ~clk;

    initial begin
        $dumpfile("fsm2_behavioral_tb.vcd");
        $dumpvars(0, fsm2_behavioral_tb);

        Reset = 1;
        #20 Reset = 0;

        Din = 0;
        #20 Din = 1;
        #20 Din = 0;
        #20 Din = 1;
        #20 Din = 0;
        #20 $finish;
    end

endmodule

module fsm2_behavioral_wb;

    reg clk;
    reg Reset;
    reg Din;
    wire Dout;

    fsm2_behavioral DUT (
        .clk(clk),
        .Reset(Reset),
        .Din(Din),
        .Dout(Dout)
    );

    initial begin
        clk = 0;
    end

    always #5 clk <= ~clk;

    initial begin
        $monitor("Time %0t, Reset: %b, Din: %b, Dout: %b, clock :%b  current_state: %b", $time, Reset, Din, Dout, clk, DUT.state);
        $dumpfile("fsm2_behavioral_wb.vcd");
        $dumpvars(0, fsm2_behavioral_wb);

        Reset = 1;
        #20 Reset = 0;

        Din = 0;
        #10 Din = 1;
        #10 Din = 0;
        #10 Din = 1;
        #10 Din = 0;
        #10 Din = 1;
        #10 Din = 0;

        #50 $finish;
    end

endmodule

Computer_Organization_&_Architecture/Ch-8 june21/exer/fsm2_behavioral_tb.vcd
$date
	Fri Jun 21 16:19:11 2024
$end
$version
	Icarus Verilog
$end
$timescale
	1s
$end
$scope module fsm2_behavioral_tb $end
$var wire 1 ! Dout $end
$var parameter 32 " CLK_PERIOD $end
$var reg 1 # Din $end
$var reg 1 $ Reset $end
$var reg 1 % clk $end
$scope module DUT $end
$var wire 1 # Din $end
$var wire 1 $ Reset $end
$var wire 1 % clk $end
$var parameter 2 & S0 $end
$var parameter 2 ' S1 $end
$var parameter 2 ( S2 $end
$var parameter 2 ) S3 $end
$var reg 1 ! Dout $end
$var reg 2 * next_state [1:0] $end
$var reg 2 + state [1:0] $end
$upscope $end
$upscope $end
$scope module fsm2_behavioral_wb $end
$var wire 1 , Dout $end
$var reg 1 - Din $end
$var reg 1 . Reset $end
$var reg 1 / clk $end
$scope module DUT $end
$var wire 1 - Din $end
$var wire 1 . Reset $end
$var wire 1 / clk $end
$var parameter 2 0 S0 $end
$var parameter 2 1 S1 $end
$var parameter 2 2 S2 $end
$var parameter 2 3 S3 $end
$var reg 1 , Dout $end
$var reg 2 4 next_state [1:0] $end
$var reg 2 5 state [1:0] $end
$upscope $end
$upscope $end
$enddefinitions $end
$comment Show the parameter values. $end
$dumpall
b11 3
b10 2
b1 1
b0 0
b11 )
b10 (
b1 '
b0 &
b1010 "
$end
#0
$dumpvars
b0 5
b0 4
0/
1.
x-
0,
b0 +
b0 *
x%
1$
x#
0!
$end
#5
1/
#10
0/
#15
1/
#20
0/
0-
0.
0#
0$
#25
1/
#30
0/
1,
b1 4
1-
#35
0,
b11 4
b1 5
1/
#40
0/
1,
b10 4
1!
b1 *
0-
1#
#45
0,
b0 4
b10 5
1/
#50
0/
1,
b11 4
1-
#55
b0 4
b11 5
1/
#60
0/
0,
b11 4
0!
b0 *
0-
0#
#65
1/
#70
0/
1,
b0 4
1-
#75
b1 4
b0 5
1/
#80
0/
0,
b0 4
1!
b1 *
0-
1#
#85
1/
#90
0/
#95
1/
#100
0/
0!
b0 *
0#
